{
	"BASE_MAP": [
		{
			"MAP_URL": "temp.png",
			"MAP_BOUNDARY_TL_LAT": 36.990460171627,
			"MAP_BOUNDARY_TL_LNG": 129.17991803276,
			"MAP_BOUNDARY_BR_LAT": 36.005947700659,
			"MAP_BOUNDARY_BR_LNG": 130.17090163933997
		}
	],
	"TODAY_DATE": {
		"DATE": "2021년 12월 21일",
		"TIME": "9시",
		"LUNAR_DATE": "음력 11월 18일"
	},
	"WATER_TEMP_WAVE_HEIGHT": [],
	"LOCAL_WATER_TEMP_WAVE_HEIGHT": [],
	"LOCAL_WATER_TEMP_WAVE_HEIGHT_WIND": [
		{
			"ID": "LWTWHW_23",
			"LAT": 36.3627,
			"LON": 129.4771,
			"WATER_TEMP": "12.9",
			"WAVE_HEIGHT": "0.1",
			"WIND": "11",
			"WIND_DIR": " 9"
		},
		{
			"ID": "LWTWHW_31",
			"LAT": 36.1819,
			"LON": 129.5762,
			"WATER_TEMP": "12.7",
			"WAVE_HEIGHT": "0.1",
			"WIND": "18",
			"WIND_DIR": " 9"
		},
		{
			"ID": "LWTWHW_35",
			"LAT": 36.5434,
			"LON": 129.5762,
			"WATER_TEMP": "13.0",
			"WAVE_HEIGHT": "0.1",
			"WIND": "16",
			"WIND_DIR": "14"
		},
		{
			"ID": "LWTWHW_39",
			"LAT": 36.9049,
			"LON": 129.5762,
			"WATER_TEMP": "13.0",
			"WAVE_HEIGHT": "0.1",
			"WIND": "13",
			"WIND_DIR": " 6"
		},
		{
			"ID": "LWTWHW_50",
			"LAT": 36.0915,
			"LON": 129.7746,
			"WATER_TEMP": "13.1",
			"WAVE_HEIGHT": "0.1",
			"WIND": "18",
			"WIND_DIR": " 9"
		},
		{
			"ID": "LWTWHW_53",
			"LAT": 36.3627,
			"LON": 129.7746,
			"WATER_TEMP": "12.8",
			"WAVE_HEIGHT": "0.1",
			"WIND": "17",
			"WIND_DIR": "15"
		},
		{
			"ID": "LWTWHW_57",
			"LAT": 36.7242,
			"LON": 129.7746,
			"WATER_TEMP": "12.9",
			"WAVE_HEIGHT": "0.1",
			"WIND": "15",
			"WIND_DIR": "11"
		},
		{
			"ID": "LWTWHW_71",
			"LAT": 36.1819,
			"LON": 129.9729,
			"WATER_TEMP": "12.2",
			"WAVE_HEIGHT": "0.1",
			"WIND": "16",
			"WIND_DIR": "19"
		},
		{
			"ID": "LWTWHW_75",
			"LAT": 36.5434,
			"LON": 129.9729,
			"WATER_TEMP": "12.5",
			"WAVE_HEIGHT": "0.1",
			"WIND": "12",
			"WIND_DIR": " 2"
		},
		{
			"ID": "LWTWHW_79",
			"LAT": 36.9049,
			"LON": 129.9729,
			"WATER_TEMP": "12.2",
			"WAVE_HEIGHT": "0.1",
			"WIND": "12",
			"WIND_DIR": "11"
		},
		{
			"ID": "LWTWHW_83",
			"LAT": 36.3627,
			"LON": 130.0721,
			"WATER_TEMP": "11.6",
			"WAVE_HEIGHT": "0.1",
			"WIND": "11",
			"WIND_DIR": "360"
		},
		{
			"ID": "LWTWHW_87",
			"LAT": 36.7242,
			"LON": 130.0721,
			"WATER_TEMP": "12.1",
			"WAVE_HEIGHT": "0.1",
			"WIND": "11",
			"WIND_DIR": " 1"
		}
	],
	"S111_CUR": [
		{
			"ID": "S111_24",
			"LAT": 36.2271,
			"LON": 129.4275,
			"CUR_SPD": "0.0356",
			"CUR_DIR": "146.7949"
		},
		{
			"ID": "S111_25",
			"LAT": 36.3175,
			"LON": 129.4275,
			"CUR_SPD": "0.0621",
			"CUR_DIR": "165.6946"
		},
		{
			"ID": "S111_34",
			"LAT": 36.1367,
			"LON": 129.5266,
			"CUR_SPD": "0.0755",
			"CUR_DIR": "83.9782"
		},
		{
			"ID": "S111_35",
			"LAT": 36.2271,
			"LON": 129.5266,
			"CUR_SPD": "0.0956",
			"CUR_DIR": "125.9614"
		},
		{
			"ID": "S111_36",
			"LAT": 36.3175,
			"LON": 129.5266,
			"CUR_SPD": "0.0586",
			"CUR_DIR": "130.4212"
		},
		{
			"ID": "S111_37",
			"LAT": 36.4078,
			"LON": 129.5266,
			"CUR_SPD": "0.0832",
			"CUR_DIR": "127.2983"
		},
		{
			"ID": "S111_38",
			"LAT": 36.4982,
			"LON": 129.5266,
			"CUR_SPD": "0.1061",
			"CUR_DIR": "123.9900"
		},
		{
			"ID": "S111_39",
			"LAT": 36.5886,
			"LON": 129.5266,
			"CUR_SPD": "0.1440",
			"CUR_DIR": "99.8395"
		},
		{
			"ID": "S111_40",
			"LAT": 36.679,
			"LON": 129.5266,
			"CUR_SPD": "0.1443",
			"CUR_DIR": "149.3705"
		},
		{
			"ID": "S111_41",
			"LAT": 36.7693,
			"LON": 129.5266,
			"CUR_SPD": "0.2746",
			"CUR_DIR": "153.7946"
		},
		{
			"ID": "S111_42",
			"LAT": 36.8597,
			"LON": 129.5266,
			"CUR_SPD": "0.2379",
			"CUR_DIR": "150.6769"
		},
		{
			"ID": "S111_43",
			"LAT": 36.9501,
			"LON": 129.5266,
			"CUR_SPD": "0.1240",
			"CUR_DIR": "172.2036"
		},
		{
			"ID": "S111_44",
			"LAT": 36.0463,
			"LON": 129.6258,
			"CUR_SPD": "0.1950",
			"CUR_DIR": "121.3427"
		},
		{
			"ID": "S111_45",
			"LAT": 36.1367,
			"LON": 129.6258,
			"CUR_SPD": "0.1675",
			"CUR_DIR": "145.3502"
		},
		{
			"ID": "S111_46",
			"LAT": 36.2271,
			"LON": 129.6258,
			"CUR_SPD": "0.1306",
			"CUR_DIR": "120.7469"
		},
		{
			"ID": "S111_47",
			"LAT": 36.3175,
			"LON": 129.6258,
			"CUR_SPD": "0.0263",
			"CUR_DIR": "17.2632"
		},
		{
			"ID": "S111_48",
			"LAT": 36.4078,
			"LON": 129.6258,
			"CUR_SPD": "0.0988",
			"CUR_DIR": "64.2669"
		},
		{
			"ID": "S111_49",
			"LAT": 36.4982,
			"LON": 129.6258,
			"CUR_SPD": "0.1305",
			"CUR_DIR": "83.7084"
		},
		{
			"ID": "S111_50",
			"LAT": 36.5886,
			"LON": 129.6258,
			"CUR_SPD": "0.1307",
			"CUR_DIR": "102.6382"
		},
		{
			"ID": "S111_51",
			"LAT": 36.679,
			"LON": 129.6258,
			"CUR_SPD": "0.1814",
			"CUR_DIR": "106.1894"
		},
		{
			"ID": "S111_52",
			"LAT": 36.7693,
			"LON": 129.6258,
			"CUR_SPD": "0.2506",
			"CUR_DIR": "140.5288"
		},
		{
			"ID": "S111_53",
			"LAT": 36.8597,
			"LON": 129.6258,
			"CUR_SPD": "0.2209",
			"CUR_DIR": "144.4459"
		},
		{
			"ID": "S111_54",
			"LAT": 36.9501,
			"LON": 129.6258,
			"CUR_SPD": "0.2295",
			"CUR_DIR": "157.9752"
		},
		{
			"ID": "S111_55",
			"LAT": 36.0463,
			"LON": 129.725,
			"CUR_SPD": "0.0931",
			"CUR_DIR": "104.4312"
		},
		{
			"ID": "S111_56",
			"LAT": 36.1367,
			"LON": 129.725,
			"CUR_SPD": "0.0804",
			"CUR_DIR": "55.1234"
		},
		{
			"ID": "S111_57",
			"LAT": 36.2271,
			"LON": 129.725,
			"CUR_SPD": "0.0653",
			"CUR_DIR": "125.9959"
		},
		{
			"ID": "S111_58",
			"LAT": 36.3175,
			"LON": 129.725,
			"CUR_SPD": "0.1997",
			"CUR_DIR": "152.2154"
		},
		{
			"ID": "S111_59",
			"LAT": 36.4078,
			"LON": 129.725,
			"CUR_SPD": "0.1829",
			"CUR_DIR": "147.6465"
		},
		{
			"ID": "S111_60",
			"LAT": 36.4982,
			"LON": 129.725,
			"CUR_SPD": "0.2832",
			"CUR_DIR": "147.7699"
		},
		{
			"ID": "S111_61",
			"LAT": 36.5886,
			"LON": 129.725,
			"CUR_SPD": "0.2903",
			"CUR_DIR": "128.9781"
		},
		{
			"ID": "S111_62",
			"LAT": 36.679,
			"LON": 129.725,
			"CUR_SPD": "0.1887",
			"CUR_DIR": "102.2557"
		},
		{
			"ID": "S111_63",
			"LAT": 36.7693,
			"LON": 129.725,
			"CUR_SPD": "0.1387",
			"CUR_DIR": "43.8366"
		},
		{
			"ID": "S111_64",
			"LAT": 36.8597,
			"LON": 129.725,
			"CUR_SPD": "0.1913",
			"CUR_DIR": "94.1539"
		},
		{
			"ID": "S111_65",
			"LAT": 36.9501,
			"LON": 129.725,
			"CUR_SPD": "0.3635",
			"CUR_DIR": "139.5567"
		},
		{
			"ID": "S111_66",
			"LAT": 36.0463,
			"LON": 129.8242,
			"CUR_SPD": "0.2736",
			"CUR_DIR": "161.9238"
		},
		{
			"ID": "S111_67",
			"LAT": 36.1367,
			"LON": 129.8242,
			"CUR_SPD": "0.3924",
			"CUR_DIR": "148.1533"
		},
		{
			"ID": "S111_68",
			"LAT": 36.2271,
			"LON": 129.8242,
			"CUR_SPD": "0.5350",
			"CUR_DIR": "152.2870"
		},
		{
			"ID": "S111_69",
			"LAT": 36.3175,
			"LON": 129.8242,
			"CUR_SPD": "0.5806",
			"CUR_DIR": "162.0217"
		},
		{
			"ID": "S111_70",
			"LAT": 36.4078,
			"LON": 129.8242,
			"CUR_SPD": "0.4429",
			"CUR_DIR": "-179.9780"
		},
		{
			"ID": "S111_71",
			"LAT": 36.4982,
			"LON": 129.8242,
			"CUR_SPD": "0.3842",
			"CUR_DIR": "178.8978"
		},
		{
			"ID": "S111_72",
			"LAT": 36.5886,
			"LON": 129.8242,
			"CUR_SPD": "0.3378",
			"CUR_DIR": "166.3260"
		},
		{
			"ID": "S111_73",
			"LAT": 36.679,
			"LON": 129.8242,
			"CUR_SPD": "0.3467",
			"CUR_DIR": "159.2508"
		},
		{
			"ID": "S111_74",
			"LAT": 36.7693,
			"LON": 129.8242,
			"CUR_SPD": "0.3755",
			"CUR_DIR": "148.1272"
		},
		{
			"ID": "S111_75",
			"LAT": 36.8597,
			"LON": 129.8242,
			"CUR_SPD": "0.4486",
			"CUR_DIR": "144.6959"
		},
		{
			"ID": "S111_76",
			"LAT": 36.9501,
			"LON": 129.8242,
			"CUR_SPD": "0.5826",
			"CUR_DIR": "133.9944"
		},
		{
			"ID": "S111_77",
			"LAT": 36.0463,
			"LON": 129.9234,
			"CUR_SPD": "0.6753",
			"CUR_DIR": "162.6207"
		},
		{
			"ID": "S111_78",
			"LAT": 36.1367,
			"LON": 129.9234,
			"CUR_SPD": "0.8493",
			"CUR_DIR": "149.3598"
		},
		{
			"ID": "S111_79",
			"LAT": 36.2271,
			"LON": 129.9234,
			"CUR_SPD": "0.7359",
			"CUR_DIR": "156.6745"
		},
		{
			"ID": "S111_80",
			"LAT": 36.3175,
			"LON": 129.9234,
			"CUR_SPD": "0.7601",
			"CUR_DIR": "169.1404"
		},
		{
			"ID": "S111_81",
			"LAT": 36.4078,
			"LON": 129.9234,
			"CUR_SPD": "0.7996",
			"CUR_DIR": "179.3516"
		},
		{
			"ID": "S111_82",
			"LAT": 36.4982,
			"LON": 129.9234,
			"CUR_SPD": "0.8369",
			"CUR_DIR": "-172.7518"
		},
		{
			"ID": "S111_83",
			"LAT": 36.5886,
			"LON": 129.9234,
			"CUR_SPD": "0.7586",
			"CUR_DIR": "-176.1552"
		},
		{
			"ID": "S111_84",
			"LAT": 36.679,
			"LON": 129.9234,
			"CUR_SPD": "0.7567",
			"CUR_DIR": "178.1469"
		},
		{
			"ID": "S111_85",
			"LAT": 36.7693,
			"LON": 129.9234,
			"CUR_SPD": "0.7751",
			"CUR_DIR": "168.6792"
		},
		{
			"ID": "S111_86",
			"LAT": 36.8597,
			"LON": 129.9234,
			"CUR_SPD": "0.7951",
			"CUR_DIR": "156.9103"
		},
		{
			"ID": "S111_87",
			"LAT": 36.9501,
			"LON": 129.9234,
			"CUR_SPD": "0.6946",
			"CUR_DIR": "144.9889"
		},
		{
			"ID": "S111_88",
			"LAT": 36.0463,
			"LON": 130.0225,
			"CUR_SPD": "0.9872",
			"CUR_DIR": "161.3695"
		},
		{
			"ID": "S111_89",
			"LAT": 36.1367,
			"LON": 130.0225,
			"CUR_SPD": "0.8359",
			"CUR_DIR": "153.5251"
		},
		{
			"ID": "S111_90",
			"LAT": 36.2271,
			"LON": 130.0225,
			"CUR_SPD": "0.7406",
			"CUR_DIR": "156.9631"
		},
		{
			"ID": "S111_91",
			"LAT": 36.3175,
			"LON": 130.0225,
			"CUR_SPD": "0.6845",
			"CUR_DIR": "167.1623"
		},
		{
			"ID": "S111_92",
			"LAT": 36.4078,
			"LON": 130.0225,
			"CUR_SPD": "0.7382",
			"CUR_DIR": "174.6876"
		},
		{
			"ID": "S111_93",
			"LAT": 36.4982,
			"LON": 130.0225,
			"CUR_SPD": "0.8056",
			"CUR_DIR": "-179.3207"
		},
		{
			"ID": "S111_94",
			"LAT": 36.5886,
			"LON": 130.0225,
			"CUR_SPD": "0.9550",
			"CUR_DIR": "-174.2820"
		},
		{
			"ID": "S111_95",
			"LAT": 36.679,
			"LON": 130.0225,
			"CUR_SPD": "1.0574",
			"CUR_DIR": "-179.9288"
		},
		{
			"ID": "S111_96",
			"LAT": 36.7693,
			"LON": 130.0225,
			"CUR_SPD": "1.0600",
			"CUR_DIR": "170.6414"
		},
		{
			"ID": "S111_97",
			"LAT": 36.8597,
			"LON": 130.0225,
			"CUR_SPD": "0.9082",
			"CUR_DIR": "162.2921"
		},
		{
			"ID": "S111_98",
			"LAT": 36.9501,
			"LON": 130.0225,
			"CUR_SPD": "0.6706",
			"CUR_DIR": "158.6795"
		},
		{
			"ID": "S111_99",
			"LAT": 36.0463,
			"LON": 130.1217,
			"CUR_SPD": "0.7094",
			"CUR_DIR": "151.3657"
		},
		{
			"ID": "S111_100",
			"LAT": 36.1367,
			"LON": 130.1217,
			"CUR_SPD": "0.6615",
			"CUR_DIR": "151.8866"
		},
		{
			"ID": "S111_101",
			"LAT": 36.2271,
			"LON": 130.1217,
			"CUR_SPD": "0.6104",
			"CUR_DIR": "154.7511"
		},
		{
			"ID": "S111_102",
			"LAT": 36.3175,
			"LON": 130.1217,
			"CUR_SPD": "0.5013",
			"CUR_DIR": "163.8378"
		},
		{
			"ID": "S111_103",
			"LAT": 36.4078,
			"LON": 130.1217,
			"CUR_SPD": "0.4723",
			"CUR_DIR": "176.5863"
		},
		{
			"ID": "S111_104",
			"LAT": 36.4982,
			"LON": 130.1217,
			"CUR_SPD": "0.5284",
			"CUR_DIR": "-178.4909"
		},
		{
			"ID": "S111_105",
			"LAT": 36.5886,
			"LON": 130.1217,
			"CUR_SPD": "0.6834",
			"CUR_DIR": "-170.8880"
		},
		{
			"ID": "S111_106",
			"LAT": 36.679,
			"LON": 130.1217,
			"CUR_SPD": "0.7886",
			"CUR_DIR": "-174.1736"
		},
		{
			"ID": "S111_107",
			"LAT": 36.7693,
			"LON": 130.1217,
			"CUR_SPD": "0.7513",
			"CUR_DIR": "178.5506"
		},
		{
			"ID": "S111_108",
			"LAT": 36.8597,
			"LON": 130.1217,
			"CUR_SPD": "0.7239",
			"CUR_DIR": "171.0969"
		},
		{
			"ID": "S111_109",
			"LAT": 36.9501,
			"LON": 130.1217,
			"CUR_SPD": "0.7250",
			"CUR_DIR": "160.6657"
		}
	],
	"FLOOD_RISK_AREA": [
		{
			"ID": "FRA_01",
			"NAME": "왕돌초",
			"MARKER_POS": "R",
			"LON": 129.732,
			"LAT": 36.719,
			"FLOOD": "T",
			"DISPLAY": "N",
			"ATTENTION_SPAN": [
				"    ",
				"    "
			]
		},
		{
			"ID": "FRA_02",
			"NAME": "후포",
			"MARKER_POS": "R",
			"LON": 129.453,
			"LAT": 36.678000000000004,
			"FLOOD": "T",
			"DISPLAY": "N",
			"ATTENTION_SPAN": [
				"    ",
				"    "
			]
		},
		{
			"ID": "FRA_03",
			"NAME": "포항",
			"MARKER_POS": "R",
			"LON": 129.374,
			"LAT": 36.051,
			"FLOOD": "T",
			"DISPLAY": "N",
			"ATTENTION_SPAN": [
				"    ",
				"    "
			]
		}
	],
	"CURRENT_INFO": []
}