{
	"BASE_MAP": [
		{
			"MAP_URL": "temp.png",
			"MAP_BOUNDARY_TL_LAT": 38.15525882601,
			"MAP_BOUNDARY_TL_LNG": 124.38483606557,
			"MAP_BOUNDARY_BR_LAT": 37.157973983923995,
			"MAP_BOUNDARY_BR_LNG": 125.88729508196998
		}
	],
	"TODAY_DATE": {
		"DATE": "2021년 12월 18일",
		"TIME": "16시",
		"LUNAR_DATE": "음력 11월 15일"
	},
	"WATER_TEMP_WAVE_HEIGHT": [],
	"LOCAL_WATER_TEMP_WAVE_HEIGHT": [],
	"LOCAL_WATER_TEMP_WAVE_HEIGHT_WIND": [
		{
			"ID": "LWTWHW_0",
			"LAT": 37.2486,
			"LON": 124.485,
			"WATER_TEMP": "10.4",
			"WAVE_HEIGHT": "1.8",
			"WIND": "12",
			"WIND_DIR": "10"
		},
		{
			"ID": "LWTWHW_4",
			"LAT": 37.6113,
			"LON": 124.485,
			"WATER_TEMP": "9.8",
			"WAVE_HEIGHT": "1.7",
			"WIND": "12",
			"WIND_DIR": "12"
		},
		{
			"ID": "LWTWHW_8",
			"LAT": 37.974,
			"LON": 124.485,
			"WATER_TEMP": "10.7",
			"WAVE_HEIGHT": "1.6",
			"WIND": "13",
			"WIND_DIR": "13"
		},
		{
			"ID": "LWTWHW_16",
			"LAT": 37.7926,
			"LON": 124.5851,
			"WATER_TEMP": "10.2",
			"WAVE_HEIGHT": "1.6",
			"WIND": "12",
			"WIND_DIR": "12"
		},
		{
			"ID": "LWTWHW_32",
			"LAT": 37.4299,
			"LON": 124.7855,
			"WATER_TEMP": "10.0",
			"WAVE_HEIGHT": "1.8",
			"WIND": "12",
			"WIND_DIR": "10"
		},
		{
			"ID": "LWTWHW_40",
			"LAT": 37.2486,
			"LON": 124.8856,
			"WATER_TEMP": "10.0",
			"WAVE_HEIGHT": "1.9",
			"WIND": "12",
			"WIND_DIR": " 8"
		},
		{
			"ID": "LWTWHW_44",
			"LAT": 37.6113,
			"LON": 124.8856,
			"WATER_TEMP": "10.2",
			"WAVE_HEIGHT": "1.5",
			"WIND": "12",
			"WIND_DIR": "10"
		},
		{
			"ID": "LWTWHW_48",
			"LAT": 37.974,
			"LON": 124.8856,
			"WATER_TEMP": "10.6",
			"WAVE_HEIGHT": "0.7",
			"WIND": " 9",
			"WIND_DIR": "13"
		},
		{
			"ID": "LWTWHW_62",
			"LAT": 37.4299,
			"LON": 125.086,
			"WATER_TEMP": "10.0",
			"WAVE_HEIGHT": "1.6",
			"WIND": "12",
			"WIND_DIR": " 5"
		},
		{
			"ID": "LWTWHW_66",
			"LAT": 37.7926,
			"LON": 125.086,
			"WATER_TEMP": "9.6",
			"WAVE_HEIGHT": "0.4",
			"WIND": "12",
			"WIND_DIR": "10"
		},
		{
			"ID": "LWTWHW_80",
			"LAT": 37.2486,
			"LON": 125.2863,
			"WATER_TEMP": "9.8",
			"WAVE_HEIGHT": "1.8",
			"WIND": "12",
			"WIND_DIR": " 5"
		},
		{
			"ID": "LWTWHW_84",
			"LAT": 37.6113,
			"LON": 125.2863,
			"WATER_TEMP": "10.2",
			"WAVE_HEIGHT": "0.9",
			"WIND": "12",
			"WIND_DIR": " 8"
		},
		{
			"ID": "LWTWHW_102",
			"LAT": 37.4299,
			"LON": 125.4866,
			"WATER_TEMP": "9.0",
			"WAVE_HEIGHT": "1.1",
			"WIND": "12",
			"WIND_DIR": " 5"
		},
		{
			"ID": "LWTWHW_120",
			"LAT": 37.2486,
			"LON": 125.6869,
			"WATER_TEMP": "9.1",
			"WAVE_HEIGHT": "1.2",
			"WIND": "12",
			"WIND_DIR": " 4"
		},
		{
			"ID": "LWTWHW_126",
			"LAT": 37.7926,
			"LON": 125.6869,
			"WATER_TEMP": "8.8",
			"WAVE_HEIGHT": "0.2",
			"WIND": "12",
			"WIND_DIR": " 7"
		},
		{
			"ID": "LWTWHW_134",
			"LAT": 37.6113,
			"LON": 125.7871,
			"WATER_TEMP": "8.4",
			"WAVE_HEIGHT": "0.6",
			"WIND": "12",
			"WIND_DIR": " 7"
		}
	],
	"S111_CUR": [
		{
			"ID": "S111_001",
			"LAT": 37.2033,
			"LON": 124.4349,
			"CUR_SPD": "0.4502",
			"CUR_DIR": "26.3864"
		},
		{
			"ID": "S111_002",
			"LAT": 37.294,
			"LON": 124.4349,
			"CUR_SPD": "0.4543",
			"CUR_DIR": "25.5883"
		},
		{
			"ID": "S111_003",
			"LAT": 37.3846,
			"LON": 124.4349,
			"CUR_SPD": "0.4384",
			"CUR_DIR": "25.8348"
		},
		{
			"ID": "S111_004",
			"LAT": 37.4753,
			"LON": 124.4349,
			"CUR_SPD": "0.3869",
			"CUR_DIR": "30.4979"
		},
		{
			"ID": "S111_005",
			"LAT": 37.566,
			"LON": 124.4349,
			"CUR_SPD": "0.4125",
			"CUR_DIR": "28.5504"
		},
		{
			"ID": "S111_006",
			"LAT": 37.6566,
			"LON": 124.4349,
			"CUR_SPD": "0.4330",
			"CUR_DIR": "21.4558"
		},
		{
			"ID": "S111_007",
			"LAT": 37.7473,
			"LON": 124.4349,
			"CUR_SPD": "0.4520",
			"CUR_DIR": "7.1113"
		},
		{
			"ID": "S111_008",
			"LAT": 37.8379,
			"LON": 124.4349,
			"CUR_SPD": "0.3584",
			"CUR_DIR": "27.8348"
		},
		{
			"ID": "S111_009",
			"LAT": 37.9286,
			"LON": 124.4349,
			"CUR_SPD": "0.3906",
			"CUR_DIR": "28.7424"
		},
		{
			"ID": "S111_010",
			"LAT": 38.0193,
			"LON": 124.4349,
			"CUR_SPD": "0.5013",
			"CUR_DIR": "25.9193"
		},
		{
			"ID": "S111_011",
			"LAT": 38.1099,
			"LON": 124.4349,
			"CUR_SPD": "0.5820",
			"CUR_DIR": "25.6687"
		},
		{
			"ID": "S111_012",
			"LAT": 37.2033,
			"LON": 124.5351,
			"CUR_SPD": "0.4351",
			"CUR_DIR": "22.3316"
		},
		{
			"ID": "S111_013",
			"LAT": 37.294,
			"LON": 124.5351,
			"CUR_SPD": "0.4529",
			"CUR_DIR": "23.4123"
		},
		{
			"ID": "S111_014",
			"LAT": 37.3846,
			"LON": 124.5351,
			"CUR_SPD": "0.4687",
			"CUR_DIR": "23.0793"
		},
		{
			"ID": "S111_015",
			"LAT": 37.4753,
			"LON": 124.5351,
			"CUR_SPD": "0.4546",
			"CUR_DIR": "19.8944"
		},
		{
			"ID": "S111_016",
			"LAT": 37.566,
			"LON": 124.5351,
			"CUR_SPD": "0.4233",
			"CUR_DIR": "20.8858"
		},
		{
			"ID": "S111_017",
			"LAT": 37.6566,
			"LON": 124.5351,
			"CUR_SPD": "0.4657",
			"CUR_DIR": "7.3854"
		},
		{
			"ID": "S111_018",
			"LAT": 37.7473,
			"LON": 124.5351,
			"CUR_SPD": "0.4521",
			"CUR_DIR": "7.9650"
		},
		{
			"ID": "S111_019",
			"LAT": 37.8379,
			"LON": 124.5351,
			"CUR_SPD": "0.4822",
			"CUR_DIR": "7.7687"
		},
		{
			"ID": "S111_020",
			"LAT": 37.9286,
			"LON": 124.5351,
			"CUR_SPD": "0.6298",
			"CUR_DIR": "3.6759"
		},
		{
			"ID": "S111_021",
			"LAT": 38.0193,
			"LON": 124.5351,
			"CUR_SPD": "0.5669",
			"CUR_DIR": "14.4482"
		},
		{
			"ID": "S111_022",
			"LAT": 38.1099,
			"LON": 124.5351,
			"CUR_SPD": "0.5581",
			"CUR_DIR": "15.2192"
		},
		{
			"ID": "S111_023",
			"LAT": 37.2033,
			"LON": 124.6352,
			"CUR_SPD": "0.4700",
			"CUR_DIR": "19.5039"
		},
		{
			"ID": "S111_024",
			"LAT": 37.294,
			"LON": 124.6352,
			"CUR_SPD": "0.4717",
			"CUR_DIR": "19.3775"
		},
		{
			"ID": "S111_025",
			"LAT": 37.3846,
			"LON": 124.6352,
			"CUR_SPD": "0.4750",
			"CUR_DIR": "23.1158"
		},
		{
			"ID": "S111_026",
			"LAT": 37.4753,
			"LON": 124.6352,
			"CUR_SPD": "0.4555",
			"CUR_DIR": "25.6699"
		},
		{
			"ID": "S111_027",
			"LAT": 37.566,
			"LON": 124.6352,
			"CUR_SPD": "0.4427",
			"CUR_DIR": "8.6104"
		},
		{
			"ID": "S111_028",
			"LAT": 37.6566,
			"LON": 124.6352,
			"CUR_SPD": "0.4200",
			"CUR_DIR": "6.8218"
		},
		{
			"ID": "S111_029",
			"LAT": 37.7473,
			"LON": 124.6352,
			"CUR_SPD": "0.3423",
			"CUR_DIR": "2.3195"
		},
		{
			"ID": "S111_031",
			"LAT": 38.0193,
			"LON": 124.6352,
			"CUR_SPD": "0.2560",
			"CUR_DIR": "16.1661"
		},
		{
			"ID": "S111_032",
			"LAT": 38.1099,
			"LON": 124.6352,
			"CUR_SPD": "0.8798",
			"CUR_DIR": "-34.3339"
		},
		{
			"ID": "S111_033",
			"LAT": 37.2033,
			"LON": 124.7354,
			"CUR_SPD": "0.4484",
			"CUR_DIR": "19.9789"
		},
		{
			"ID": "S111_034",
			"LAT": 37.294,
			"LON": 124.7354,
			"CUR_SPD": "0.4222",
			"CUR_DIR": "22.7990"
		},
		{
			"ID": "S111_035",
			"LAT": 37.3846,
			"LON": 124.7354,
			"CUR_SPD": "0.4175",
			"CUR_DIR": "30.2050"
		},
		{
			"ID": "S111_036",
			"LAT": 37.4753,
			"LON": 124.7354,
			"CUR_SPD": "0.4419",
			"CUR_DIR": "35.1395"
		},
		{
			"ID": "S111_037",
			"LAT": 37.566,
			"LON": 124.7354,
			"CUR_SPD": "0.4073",
			"CUR_DIR": "15.4573"
		},
		{
			"ID": "S111_038",
			"LAT": 37.6566,
			"LON": 124.7354,
			"CUR_SPD": "0.3354",
			"CUR_DIR": "23.5922"
		},
		{
			"ID": "S111_042",
			"LAT": 38.0193,
			"LON": 124.7354,
			"CUR_SPD": "0.3452",
			"CUR_DIR": "-39.5923"
		},
		{
			"ID": "S111_044",
			"LAT": 37.2033,
			"LON": 124.8356,
			"CUR_SPD": "0.4148",
			"CUR_DIR": "32.5224"
		},
		{
			"ID": "S111_045",
			"LAT": 37.294,
			"LON": 124.8356,
			"CUR_SPD": "0.3522",
			"CUR_DIR": "33.2017"
		},
		{
			"ID": "S111_046",
			"LAT": 37.3846,
			"LON": 124.8356,
			"CUR_SPD": "0.3862",
			"CUR_DIR": "29.8150"
		},
		{
			"ID": "S111_047",
			"LAT": 37.4753,
			"LON": 124.8356,
			"CUR_SPD": "0.4297",
			"CUR_DIR": "14.7581"
		},
		{
			"ID": "S111_048",
			"LAT": 37.566,
			"LON": 124.8356,
			"CUR_SPD": "0.4355",
			"CUR_DIR": "24.9788"
		},
		{
			"ID": "S111_049",
			"LAT": 37.6566,
			"LON": 124.8356,
			"CUR_SPD": "0.4807",
			"CUR_DIR": "42.8597"
		},
		{
			"ID": "S111_050",
			"LAT": 37.7473,
			"LON": 124.8356,
			"CUR_SPD": "0.6100",
			"CUR_DIR": "34.8676"
		},
		{
			"ID": "S111_051",
			"LAT": 37.8379,
			"LON": 124.8356,
			"CUR_SPD": "0.4307",
			"CUR_DIR": "-21.5443"
		},
		{
			"ID": "S111_052",
			"LAT": 37.9286,
			"LON": 124.8356,
			"CUR_SPD": "0.4116",
			"CUR_DIR": "-13.4682"
		},
		{
			"ID": "S111_053",
			"LAT": 38.0193,
			"LON": 124.8356,
			"CUR_SPD": "0.2783",
			"CUR_DIR": "12.2284"
		},
		{
			"ID": "S111_055",
			"LAT": 37.2033,
			"LON": 124.9357,
			"CUR_SPD": "0.4199",
			"CUR_DIR": "36.0379"
		},
		{
			"ID": "S111_056",
			"LAT": 37.294,
			"LON": 124.9357,
			"CUR_SPD": "0.3975",
			"CUR_DIR": "13.9522"
		},
		{
			"ID": "S111_057",
			"LAT": 37.3846,
			"LON": 124.9357,
			"CUR_SPD": "0.4317",
			"CUR_DIR": "13.4720"
		},
		{
			"ID": "S111_058",
			"LAT": 37.4753,
			"LON": 124.9357,
			"CUR_SPD": "0.4141",
			"CUR_DIR": "16.1589"
		},
		{
			"ID": "S111_059",
			"LAT": 37.566,
			"LON": 124.9357,
			"CUR_SPD": "0.5094",
			"CUR_DIR": "31.8203"
		},
		{
			"ID": "S111_060",
			"LAT": 37.6566,
			"LON": 124.9357,
			"CUR_SPD": "0.5261",
			"CUR_DIR": "41.1980"
		},
		{
			"ID": "S111_061",
			"LAT": 37.7473,
			"LON": 124.9357,
			"CUR_SPD": "0.4248",
			"CUR_DIR": "3.2627"
		},
		{
			"ID": "S111_062",
			"LAT": 37.8379,
			"LON": 124.9357,
			"CUR_SPD": "0.4815",
			"CUR_DIR": "1.1703"
		},
		{
			"ID": "S111_064",
			"LAT": 38.0193,
			"LON": 124.9357,
			"CUR_SPD": "0.3700",
			"CUR_DIR": "35.8300"
		},
		{
			"ID": "S111_066",
			"LAT": 37.2033,
			"LON": 125.0359,
			"CUR_SPD": "0.4237",
			"CUR_DIR": "24.5997"
		},
		{
			"ID": "S111_067",
			"LAT": 37.294,
			"LON": 125.0359,
			"CUR_SPD": "0.3801",
			"CUR_DIR": "17.9958"
		},
		{
			"ID": "S111_068",
			"LAT": 37.3846,
			"LON": 125.0359,
			"CUR_SPD": "0.4057",
			"CUR_DIR": "16.6139"
		},
		{
			"ID": "S111_069",
			"LAT": 37.4753,
			"LON": 125.0359,
			"CUR_SPD": "0.4120",
			"CUR_DIR": "23.8470"
		},
		{
			"ID": "S111_070",
			"LAT": 37.566,
			"LON": 125.0359,
			"CUR_SPD": "0.5029",
			"CUR_DIR": "39.4316"
		},
		{
			"ID": "S111_071",
			"LAT": 37.6566,
			"LON": 125.0359,
			"CUR_SPD": "0.3727",
			"CUR_DIR": "37.9061"
		},
		{
			"ID": "S111_072",
			"LAT": 37.7473,
			"LON": 125.0359,
			"CUR_SPD": "0.3318",
			"CUR_DIR": "36.7385"
		},
		{
			"ID": "S111_074",
			"LAT": 37.2033,
			"LON": 125.1361,
			"CUR_SPD": "0.3650",
			"CUR_DIR": "33.1140"
		},
		{
			"ID": "S111_075",
			"LAT": 37.294,
			"LON": 125.1361,
			"CUR_SPD": "0.3455",
			"CUR_DIR": "27.9764"
		},
		{
			"ID": "S111_076",
			"LAT": 37.3846,
			"LON": 125.1361,
			"CUR_SPD": "0.4000",
			"CUR_DIR": "18.4711"
		},
		{
			"ID": "S111_077",
			"LAT": 37.4753,
			"LON": 125.1361,
			"CUR_SPD": "0.6215",
			"CUR_DIR": "32.6146"
		},
		{
			"ID": "S111_078",
			"LAT": 37.566,
			"LON": 125.1361,
			"CUR_SPD": "0.4233",
			"CUR_DIR": "49.3004"
		},
		{
			"ID": "S111_079",
			"LAT": 37.6566,
			"LON": 125.1361,
			"CUR_SPD": "0.2926",
			"CUR_DIR": "56.5971"
		},
		{
			"ID": "S111_080",
			"LAT": 37.7473,
			"LON": 125.1361,
			"CUR_SPD": "0.3699",
			"CUR_DIR": "30.7353"
		},
		{
			"ID": "S111_082",
			"LAT": 37.2033,
			"LON": 125.2362,
			"CUR_SPD": "0.4029",
			"CUR_DIR": "33.6299"
		},
		{
			"ID": "S111_083",
			"LAT": 37.294,
			"LON": 125.2362,
			"CUR_SPD": "0.3362",
			"CUR_DIR": "34.9312"
		},
		{
			"ID": "S111_084",
			"LAT": 37.3846,
			"LON": 125.2362,
			"CUR_SPD": "0.5180",
			"CUR_DIR": "24.0836"
		},
		{
			"ID": "S111_085",
			"LAT": 37.4753,
			"LON": 125.2362,
			"CUR_SPD": "0.6216",
			"CUR_DIR": "38.6083"
		},
		{
			"ID": "S111_086",
			"LAT": 37.566,
			"LON": 125.2362,
			"CUR_SPD": "0.4180",
			"CUR_DIR": "53.3263"
		},
		{
			"ID": "S111_087",
			"LAT": 37.6566,
			"LON": 125.2362,
			"CUR_SPD": "0.2285",
			"CUR_DIR": "61.3853"
		},
		{
			"ID": "S111_089",
			"LAT": 37.2033,
			"LON": 125.3364,
			"CUR_SPD": "0.4840",
			"CUR_DIR": "29.5253"
		},
		{
			"ID": "S111_090",
			"LAT": 37.294,
			"LON": 125.3364,
			"CUR_SPD": "0.4142",
			"CUR_DIR": "48.2579"
		},
		{
			"ID": "S111_091",
			"LAT": 37.3846,
			"LON": 125.3364,
			"CUR_SPD": "0.6235",
			"CUR_DIR": "32.5994"
		},
		{
			"ID": "S111_092",
			"LAT": 37.4753,
			"LON": 125.3364,
			"CUR_SPD": "0.5392",
			"CUR_DIR": "32.9680"
		},
		{
			"ID": "S111_093",
			"LAT": 37.566,
			"LON": 125.3364,
			"CUR_SPD": "0.4407",
			"CUR_DIR": "56.9036"
		},
		{
			"ID": "S111_094",
			"LAT": 37.6566,
			"LON": 125.3364,
			"CUR_SPD": "0.2807",
			"CUR_DIR": "89.0903"
		},
		{
			"ID": "S111_095",
			"LAT": 37.2033,
			"LON": 125.4366,
			"CUR_SPD": "0.5704",
			"CUR_DIR": "30.3303"
		},
		{
			"ID": "S111_096",
			"LAT": 37.294,
			"LON": 125.4366,
			"CUR_SPD": "0.5648",
			"CUR_DIR": "55.3288"
		},
		{
			"ID": "S111_097",
			"LAT": 37.3846,
			"LON": 125.4366,
			"CUR_SPD": "0.7020",
			"CUR_DIR": "28.4678"
		},
		{
			"ID": "S111_098",
			"LAT": 37.4753,
			"LON": 125.4366,
			"CUR_SPD": "0.5636",
			"CUR_DIR": "29.4987"
		},
		{
			"ID": "S111_099",
			"LAT": 37.566,
			"LON": 125.4366,
			"CUR_SPD": "0.4296",
			"CUR_DIR": "49.4508"
		},
		{
			"ID": "S111_100",
			"LAT": 37.6566,
			"LON": 125.4366,
			"CUR_SPD": "0.6009",
			"CUR_DIR": "62.1249"
		},
		{
			"ID": "S111_101",
			"LAT": 37.2033,
			"LON": 125.5367,
			"CUR_SPD": "0.5664",
			"CUR_DIR": "30.4964"
		},
		{
			"ID": "S111_102",
			"LAT": 37.294,
			"LON": 125.5367,
			"CUR_SPD": "0.5732",
			"CUR_DIR": "53.1219"
		},
		{
			"ID": "S111_103",
			"LAT": 37.3846,
			"LON": 125.5367,
			"CUR_SPD": "0.7368",
			"CUR_DIR": "40.3848"
		},
		{
			"ID": "S111_104",
			"LAT": 37.4753,
			"LON": 125.5367,
			"CUR_SPD": "0.6177",
			"CUR_DIR": "33.7208"
		},
		{
			"ID": "S111_105",
			"LAT": 37.566,
			"LON": 125.5367,
			"CUR_SPD": "0.3839",
			"CUR_DIR": "43.8721"
		},
		{
			"ID": "S111_106",
			"LAT": 37.6566,
			"LON": 125.5367,
			"CUR_SPD": "0.5831",
			"CUR_DIR": "61.8052"
		},
		{
			"ID": "S111_108",
			"LAT": 37.2033,
			"LON": 125.6369,
			"CUR_SPD": "0.5880",
			"CUR_DIR": "24.2666"
		},
		{
			"ID": "S111_109",
			"LAT": 37.294,
			"LON": 125.6369,
			"CUR_SPD": "0.5881",
			"CUR_DIR": "42.6508"
		},
		{
			"ID": "S111_110",
			"LAT": 37.3846,
			"LON": 125.6369,
			"CUR_SPD": "0.7912",
			"CUR_DIR": "51.9208"
		},
		{
			"ID": "S111_111",
			"LAT": 37.4753,
			"LON": 125.6369,
			"CUR_SPD": "0.6812",
			"CUR_DIR": "30.6544"
		},
		{
			"ID": "S111_112",
			"LAT": 37.566,
			"LON": 125.6369,
			"CUR_SPD": "0.4413",
			"CUR_DIR": "35.5122"
		},
		{
			"ID": "S111_116",
			"LAT": 37.2033,
			"LON": 125.737,
			"CUR_SPD": "0.6568",
			"CUR_DIR": "30.7070"
		},
		{
			"ID": "S111_117",
			"LAT": 37.294,
			"LON": 125.737,
			"CUR_SPD": "0.6135",
			"CUR_DIR": "32.0718"
		},
		{
			"ID": "S111_118",
			"LAT": 37.3846,
			"LON": 125.737,
			"CUR_SPD": "0.8215",
			"CUR_DIR": "51.2592"
		},
		{
			"ID": "S111_119",
			"LAT": 37.4753,
			"LON": 125.737,
			"CUR_SPD": "0.7518",
			"CUR_DIR": "29.8347"
		},
		{
			"ID": "S111_120",
			"LAT": 37.566,
			"LON": 125.737,
			"CUR_SPD": "0.4457",
			"CUR_DIR": "64.7054"
		},
		{
			"ID": "S111_122",
			"LAT": 37.7473,
			"LON": 125.737,
			"CUR_SPD": "0.6585",
			"CUR_DIR": "58.8696"
		},
		{
			"ID": "S111_125",
			"LAT": 37.2033,
			"LON": 125.8372,
			"CUR_SPD": "0.7831",
			"CUR_DIR": "44.4926"
		},
		{
			"ID": "S111_126",
			"LAT": 37.294,
			"LON": 125.8372,
			"CUR_SPD": "0.6378",
			"CUR_DIR": "31.0461"
		},
		{
			"ID": "S111_127",
			"LAT": 37.3846,
			"LON": 125.8372,
			"CUR_SPD": "0.6267",
			"CUR_DIR": "37.7934"
		},
		{
			"ID": "S111_128",
			"LAT": 37.4753,
			"LON": 125.8372,
			"CUR_SPD": "0.8714",
			"CUR_DIR": "44.5417"
		},
		{
			"ID": "S111_129",
			"LAT": 37.566,
			"LON": 125.8372,
			"CUR_SPD": "0.7652",
			"CUR_DIR": "39.1205"
		},
		{
			"ID": "S111_130",
			"LAT": 37.6566,
			"LON": 125.8372,
			"CUR_SPD": "0.5754",
			"CUR_DIR": "17.3273"
		},
		{
			"ID": "S111_131",
			"LAT": 37.7473,
			"LON": 125.8372,
			"CUR_SPD": "0.3597",
			"CUR_DIR": "22.0382"
		}
	],
	"FLOOD_RISK_AREA": [
		{
			"ID": "FRA_01",
			"NAME": "순위도",
			"MARKER_POS": "R",
			"LON": 125.31700000000001,
			"LAT": 37.75,
			"FLOOD": "T",
			"DISPLAY": "N",
			"ATTENTION_SPAN": [
				"    ",
				"    "
			]
		},
		{
			"ID": "FRA_02",
			"NAME": "연평도",
			"MARKER_POS": "R",
			"LON": 125.7,
			"LAT": 37.65,
			"FLOOD": "T",
			"DISPLAY": "N",
			"ATTENTION_SPAN": [
				"    ",
				"    "
			]
		},
		{
			"ID": "FRA_03",
			"NAME": "옹진소청초",
			"MARKER_POS": "R",
			"LON": 124.738,
			"LAT": 37.423,
			"FLOOD": "T",
			"DISPLAY": "N",
			"ATTENTION_SPAN": [
				"    ",
				"    "
			]
		},
		{
			"ID": "FRA_04",
			"NAME": "대청도",
			"MARKER_POS": "R",
			"LON": 124.71700000000001,
			"LAT": 37.817,
			"FLOOD": "T",
			"DISPLAY": "N",
			"ATTENTION_SPAN": [
				"    ",
				"    "
			]
		},
		{
			"ID": "FRA_05",
			"NAME": "백령도",
			"MARKER_POS": "R",
			"LON": 124.73299999999999,
			"LAT": 37.95,
			"FLOOD": "T",
			"DISPLAY": "N",
			"ATTENTION_SPAN": [
				"    ",
				"    "
			]
		}
	],
	"CURRENT_INFO": [
		{
			"ID": "CUR_01",
			"NAME": "백령도",
			"LON": 124.764,
			"LAT": 37.876999999999995,
			"MARKER_POS": "R",
			"MARKER_V_POS": "B",
			"CUR_INFO": [
				{
					"MIN_CUR_TIME": "02:08",
					"MAX_CUR_TIME": "05:51",
					"CUR_DIRECT": "338",
					"CUR_SPEED": 1.5
				},
				{
					"MIN_CUR_TIME": "08:36",
					"MAX_CUR_TIME": "11:07",
					"CUR_DIRECT": "158",
					"CUR_SPEED": 1.5
				},
				{
					"MIN_CUR_TIME": "13:52",
					"MAX_CUR_TIME": "18:18",
					"CUR_DIRECT": "338",
					"CUR_SPEED": 1.9
				},
				{
					"MIN_CUR_TIME": "21:19",
					"MAX_CUR_TIME": "23:47",
					"CUR_DIRECT": "158",
					"CUR_SPEED": 1.5
				}
			],
			"DEG_FE": [
				"68",
				"248",
				"EBB"
			]
		},
		{
			"ID": "CUR_02",
			"NAME": "소청도",
			"LON": 124.691,
			"LAT": 37.725,
			"MARKER_POS": "R",
			"MARKER_V_POS": "B",
			"CUR_INFO": [
				{
					"MIN_CUR_TIME": "",
					"MAX_CUR_TIME": "00:56",
					"CUR_DIRECT": "135",
					"CUR_SPEED": 2.0
				},
				{
					"MIN_CUR_TIME": "04:14",
					"MAX_CUR_TIME": "07:06",
					"CUR_DIRECT": "293",
					"CUR_SPEED": 1.4
				},
				{
					"MIN_CUR_TIME": "09:39",
					"MAX_CUR_TIME": "13:02",
					"CUR_DIRECT": "135",
					"CUR_SPEED": 2.3
				},
				{
					"MIN_CUR_TIME": "16:01",
					"MAX_CUR_TIME": "19:15",
					"CUR_DIRECT": "315",
					"CUR_SPEED": 2.2
				}
			],
			"DEG_FE": [
				"45",
				"225",
				"EBB"
			]
		}
	]
}